odoo/addons/account_payment_method_base/README.rst
odoo/addons/account_payment_method_base/__init__.py
odoo/addons/account_payment_method_base/__manifest__.py
odoo/addons/account_payment_method_base/i18n/account_payment_method_base.pot
odoo/addons/account_payment_method_base/i18n/fr.po
odoo/addons/account_payment_method_base/i18n/it.po
odoo/addons/account_payment_method_base/i18n/pt_BR.po
odoo/addons/account_payment_method_base/models/__init__.py
odoo/addons/account_payment_method_base/models/account_payment_method.py
odoo/addons/account_payment_method_base/readme/CONTRIBUTORS.md
odoo/addons/account_payment_method_base/readme/DESCRIPTION.md
odoo/addons/account_payment_method_base/static/description/icon.png
odoo/addons/account_payment_method_base/static/description/index.html
odoo/addons/account_payment_method_base/views/account_payment_method.xml
odoo_addon_account_payment_method_base-19.0.1.0.0.2.dist-info/METADATA
odoo_addon_account_payment_method_base-19.0.1.0.0.2.dist-info/WHEEL
odoo_addon_account_payment_method_base-19.0.1.0.0.2.dist-info/top_level.txt
odoo_addon_account_payment_method_base-19.0.1.0.0.2.dist-info/RECORD
