Metadata-Version: 2.1
Name: odoo-addon-account_payment_method_base
Version: 19.0.1.0.0.2
Requires-Dist: odoo==19.0.*
Summary: Add form and list view for account.payment.method
Home-page: https://github.com/OCA/account-payment
License: AGPL-3
Author: Akretion,Odoo Community Association (OCA)
Author-email: support@odoo-community.org
Classifier: Programming Language :: Python
Classifier: Framework :: Odoo
Classifier: Framework :: Odoo :: 19.0
Classifier: License :: OSI Approved :: GNU Affero General Public License v3
Classifier: Development Status :: 6 - Mature
